lab10/__init__.py
lab10/app.py
lab10/conv.py
lab10/solv.py
twine_lab10-1.4.dist-info/METADATA
twine_lab10-1.4.dist-info/RECORD
twine_lab10-1.4.dist-info/WHEEL
twine_lab10-1.4.dist-info/top_level.txt
