Metadata-Version: 2.1
Name: twine-lab10
Version: 1.4
Summary: An example python package
Home-page: https://github.com/mikolaj965/DPP_Lab10/
Author: Mikolaj Mazurek
Author-email: mikolajmazurek@gmail.com
License: MIT
Platform: UNKNOWN
